nccompare/__init__.py
nccompare/compare/__init__.py
nccompare/compare/ncdiff.py
nccompare/conf/__init__.py
nccompare/conf/global_settings.py
nccompare/core/__init__.py
nccompare/core/main.py
nccompare/exceptions/__init__.py
nccompare/exceptions/all_nan.py
nccompare/exceptions/last_timestep.py
nccompare/management/__init__.py
nccompare/management/cli.py
nccompare/model/__init__.py
nccompare/model/compare_result.py
nccompare/model/comparison.py
nccompare/printlib/__init__.py
nccompare/printlib/formatter.py
nccompare/utils/__init__.py
nccompare/utils/log.py
nccompare/utils/module_loading.py
nccompare/utils/regex.py
nccompare-0.2.4.dist-info/LICENSE
nccompare-0.2.4.dist-info/METADATA
nccompare-0.2.4.dist-info/WHEEL
nccompare-0.2.4.dist-info/entry_points.txt
nccompare-0.2.4.dist-info/RECORD
