Metadata-Version: 2.1
Name: ncCompare
Version: 0.2.4
Summary: netCDF Comparison Tool
Author: Antonio Mariani
Author-email: antonio.mariani@cmcc.it
Requires-Python: >=3.10,<4.0
Classifier: Programming Language :: Python :: 3
Classifier: Programming Language :: Python :: 3.10
Classifier: Programming Language :: Python :: 3.11
Classifier: Programming Language :: Python :: 3.12
Requires-Dist: netcdf4 (>=1.7.1,<2.0.0)
Requires-Dist: pandas (>=2.2.2,<3.0.0)
Requires-Dist: rich (>=13.7.1,<14.0.0)
Requires-Dist: xarray (>=2024.6.0,<2025.0.0)
